Workbook

Sheet Prospectos
A1: PROSPECTOS — sprint de septiembre | D1: Amarillo: se completa a mano. Gris: se calcula solo, no escribir. La fila 3 es un ejemplo del formato y no se cuenta: cargá desde la fila 4. La mañana arranca filtrando "Próximo toque" hasta hoy.
A2: Nombre | B2: Negocio | C2: Origen | D2: Dolor | E2: 1er contacto | F2: Último toque | G2: Próximo toque | H2: Estado | I2: C | J2: F | K2: P | L2: T | M2: H | N2: V | O2: Total mensual | P2: Total × 6 | Q2: Nivel sugerido | R2: Facturación | S2: Quién decide | T2: Precio dicho | U2: Medio de pago | V2: Notas textuales
A3: Ejemplo: Javier Ortega | B3: Asesoría fiscal (Valencia) | C3: F | D3: 1 · Seguimiento de leads y respuesta lenta | E3: 46267 | F3: 46267 | G3: 46269 | H3: abierto | I3: 100 | J3: 0.2 | K3: 0.25 | L3: 200 | M3: 12 | N3: 9 | O3: =IF(COUNT(I3:L3)+COUNT(M3:N3)=0,"",IFERROR(I3*J3*K3*L3,0)+IFERROR(M3*4.3*N3,0)) | P3: =IF(O3="","",O3*6) | Q3: =IF(P3="","",IF(R3="<10k","Todavía no",IF(P3<1500,"Todavía no",IF(P3<3500,"Nivel 1","Nivel 2 o 3")))) | R3: 10–50k | S3: Él con un socio | T3: 46268 | U3: Link tarjeta USD | V3: Perdió 2 clientes en agosto. El comercial se va en octubre.
O4: =IF(COUNT(I4:L4)+COUNT(M4:N4)=0,"",IFERROR(I4*J4*K4*L4,0)+IFERROR(M4*4.3*N4,0)) | P4: =IF(O4="","",O4*6) | Q4: =IF(P4="","",IF(R4="<10k","Todavía no",IF(P4<1500,"Todavía no",IF(P4<3500,"Nivel 1","Nivel 2 o 3"))))
O5: =IF(COUNT(I5:L5)+COUNT(M5:N5)=0,"",IFERROR(I5*J5*K5*L5,0)+IFERROR(M5*4.3*N5,0)) | P5: =IF(O5="","",O5*6) | Q5: =IF(P5="","",IF(R5="<10k","Todavía no",IF(P5<1500,"Todavía no",IF(P5<3500,"Nivel 1","Nivel 2 o 3"))))
O6: =IF(COUNT(I6:L6)+COUNT(M6:N6)=0,"",IFERROR(I6*J6*K6*L6,0)+IFERROR(M6*4.3*N6,0)) | P6: =IF(O6="","",O6*6) | Q6: =IF(P6="","",IF(R6="<10k","Todavía no",IF(P6<1500,"Todavía no",IF(P6<3500,"Nivel 1","Nivel 2 o 3"))))
O7: =IF(COUNT(I7:L7)+COUNT(M7:N7)=0,"",IFERROR(I7*J7*K7*L7,0)+IFERROR(M7*4.3*N7,0)) | P7: =IF(O7="","",O7*6) | Q7: =IF(P7="","",IF(R7="<10k","Todavía no",IF(P7<1500,"Todavía no",IF(P7<3500,"Nivel 1","Nivel 2 o 3"))))
O8: =IF(COUNT(I8:L8)+COUNT(M8:N8)=0,"",IFERROR(I8*J8*K8*L8,0)+IFERROR(M8*4.3*N8,0)) | P8: =IF(O8="","",O8*6) | Q8: =IF(P8="","",IF(R8="<10k","Todavía no",IF(P8<1500,"Todavía no",IF(P8<3500,"Nivel 1","Nivel 2 o 3"))))
O9: =IF(COUNT(I9:L9)+COUNT(M9:N9)=0,"",IFERROR(I9*J9*K9*L9,0)+IFERROR(M9*4.3*N9,0)) | P9: =IF(O9="","",O9*6) | Q9: =IF(P9="","",IF(R9="<10k","Todavía no",IF(P9<1500,"Todavía no",IF(P9<3500,"Nivel 1","Nivel 2 o 3"))))
O10: =IF(COUNT(I10:L10)+COUNT(M10:N10)=0,"",IFERROR(I10*J10*K10*L10,0)+IFERROR(M10*4.3*N10,0)) | P10: =IF(O10="","",O10*6) | Q10: =IF(P10="","",IF(R10="<10k","Todavía no",IF(P10<1500,"Todavía no",IF(P10<3500,"Nivel 1","Nivel 2 o 3"))))
O11: =IF(COUNT(I11:L11)+COUNT(M11:N11)=0,"",IFERROR(I11*J11*K11*L11,0)+IFERROR(M11*4.3*N11,0)) | P11: =IF(O11="","",O11*6) | Q11: =IF(P11="","",IF(R11="<10k","Todavía no",IF(P11<1500,"Todavía no",IF(P11<3500,"Nivel 1","Nivel 2 o 3"))))
O12: =IF(COUNT(I12:L12)+COUNT(M12:N12)=0,"",IFERROR(I12*J12*K12*L12,0)+IFERROR(M12*4.3*N12,0)) | P12: =IF(O12="","",O12*6) | Q12: =IF(P12="","",IF(R12="<10k","Todavía no",IF(P12<1500,"Todavía no",IF(P12<3500,"Nivel 1","Nivel 2 o 3"))))
O13: =IF(COUNT(I13:L13)+COUNT(M13:N13)=0,"",IFERROR(I13*J13*K13*L13,0)+IFERROR(M13*4.3*N13,0)) | P13: =IF(O13="","",O13*6) | Q13: =IF(P13="","",IF(R13="<10k","Todavía no",IF(P13<1500,"Todavía no",IF(P13<3500,"Nivel 1","Nivel 2 o 3"))))
O14: =IF(COUNT(I14:L14)+COUNT(M14:N14)=0,"",IFERROR(I14*J14*K14*L14,0)+IFERROR(M14*4.3*N14,0)) | P14: =IF(O14="","",O14*6) | Q14: =IF(P14="","",IF(R14="<10k","Todavía no",IF(P14<1500,"Todavía no",IF(P14<3500,"Nivel 1","Nivel 2 o 3"))))
O15: =IF(COUNT(I15:L15)+COUNT(M15:N15)=0,"",IFERROR(I15*J15*K15*L15,0)+IFERROR(M15*4.3*N15,0)) | P15: =IF(O15="","",O15*6) | Q15: =IF(P15="","",IF(R15="<10k","Todavía no",IF(P15<1500,"Todavía no",IF(P15<3500,"Nivel 1","Nivel 2 o 3"))))
... O203: =IF(COUNT(I203:L203)+COUNT(M203:N203)=0,"",IFERROR(I203*J203*K203*L203,0)+IFERROR(M203*4.3*N203,0)) | P203: =IF(O203="","",O203*6) | Q203: =IF(P203="","",IF(R203="<10k","Todavía no",IF(P203<1500,"Todavía no",IF(P203<3500,"Nivel 1","Nivel 2 o 3"))))

Sheet Cálculo
A1: CÁLCULO EN VIVO — una sesión por vez
A2: Se completa mientras hablás. Amarillo: lo que dice el cliente. Gris: se calcula solo. Viene con el ejemplo cargado para que veas los controles en verde: borralo antes de la primera sesión real.
A4: Las seis letras | C4: hoja de números, sección 2
A5: C — consultas por mes | B5: 100
A6: F — fracción que se pierde | B6: 0.2
A7: P — conversión de las bien atendidas | B7: 0.25
A8: T — ticket: primera venta o primer mes | B8: 200
A9: H — horas manuales por semana | B9: 12
A10: V — valor de esa hora (sueldo ÷ 170) | B10: 9
A12: Consultas perdidas por mes | B12: =B5*B6
A13: Ventas en juego por mes | B13: =B12*B7
A14: Fuga comercial mensual | B14: =B13*B8
A15: Horas manuales mensuales | B15: =B9*4.3
A16: Costo de las horas | B16: =B15*B10
A17: TOTAL MENSUAL | B17: =B14+B16
A18: TOTAL × 6 (lo que decide el nivel) | B18: =B17*6
A20: Nivel sugerido | B20: =IF(B18<1500,"Todavía no",IF(B18<3500,"Nivel 1 — desde US$1.500","Nivel 2 — desde US$3.500 (Nivel 3 si además cambia procesos seguido, nadie va a ser dueño del sistema, o pide acompañamiento)"))
A21: Piso de cuota para Nivel 3 (2% de la facturación mensual) | B21: =IF(B22="","completá la facturación →",B22*0.02)
A22: Facturación mensual del cliente (para el piso del 2%) | B22: 25000
A24: El recorrido | C24: ocho pasos: de la consulta al cobro
A25: Paso 1
A26: Paso 2
A27: Paso 3
A28: Paso 4
A29: Paso 5
A30: Paso 6
A31: Paso 7
A32: Paso 8
A34: La tabla de fugas | C34: el costo se calcula solo; las tres celdas de control tienen que dar 0
A35: Dónde ocurre | B35: Tipo | C35: Veces/mes o hs/sem | D35: Minutos c/u | E35: Costo mensual | F35: Qué lo resuelve | G35: Prioridad
A36: Consulta entra por WhatsApp y se contesta al otro día | B36: comercial | C36: 12 | D36: más de 24 h | E36: =IF(C36="","",IF(B36="comercial",C36*$B$7*$B$8,IF(B36="horas",C36*4.3*$B$10,""))) | F36: Respuesta automática y aviso al que atiende | G36: 1
A37: Presupuesto enviado sin segundo intento | B37: comercial | C37: 8 | D37: — | E37: =IF(C37="","",IF(B37="comercial",C37*$B$7*$B$8,IF(B37="horas",C37*4.3*$B$10,""))) | F37: Recordatorio a las 48 h con tarea asignada | G37: 1
A38: Cargar consultas a mano en la planilla | B38: horas | C38: 4 | D38: 10 min c/u | E38: =IF(C38="","",IF(B38="comercial",C38*$B$7*$B$8,IF(B38="horas",C38*4.3*$B$10,""))) | F38: Formulario que carga solo | G38: 2
A39: Armar cada presupuesto desde cero | B39: horas | C39: 3 | D39: 15 min c/u | E39: =IF(C39="","",IF(B39="comercial",C39*$B$7*$B$8,IF(B39="horas",C39*4.3*$B$10,""))) | F39: Plantilla con datos precargados | G39: 2
A40: Contestar las mismas preguntas | B40: horas | C40: 3 | D40: 7 min c/u | E40: =IF(C40="","",IF(B40="comercial",C40*$B$7*$B$8,IF(B40="horas",C40*4.3*$B$10,""))) | F40: Respuestas guardadas | G40: 3
A41: Pasar datos a facturación | B41: horas | C41: 2 | D41: — | E41: =IF(C41="","",IF(B41="comercial",C41*$B$7*$B$8,IF(B41="horas",C41*4.3*$B$10,""))) | F41: Integración | G41: no tocar
A43: Control 1 — consultas repartidas menos C × F | B43: =IF(COUNT($C$36:$C$41)=0,"",ROUND(SUMIF($B$36:$B$41,"comercial",$C$36:$C$41)-B12,2)) | C43: Verde = cuadra. Rojo = falta repartir algo; se pregunta en la sesión, no se completa después.
A44: Control 2 — horas repartidas menos H | B44: =IF(COUNT($C$36:$C$41)=0,"",ROUND(SUMIF($B$36:$B$41,"horas",$C$36:$C$41)-B9,2))
A45: Control 3 — suma de la tabla menos el total | B45: =IF(COUNT($C$36:$C$41)=0,"",ROUND(SUM($E$36:$E$41)-B17,0))
A47: Prueba de que la planilla está bien armada: con el ejemplo cargado (100 · 20% · 25% · US$200 · 12 h · US$9) el TOTAL MENSUAL tiene que dar US$1.464 y el TOTAL × 6, unos US$8.784.

Sheet Tablero
A1: TABLERO DEL SPRINT
A2: Todo se calcula desde Prospectos. Acá no se escribe nada.
A4: Los mínimos del mes
A5: Contactos cargados | B5: =COUNTA(Prospectos!$A$4:$A$203)
A6: Conversaciones de venta (precio dicho) | B6: =COUNT(Prospectos!$T$4:$T$203) | C6: 12 | D6: objetivo del mes
A7: Diagnósticos reservados | B7: =COUNTIF(Prospectos!$H$4:$H$203,"reservó")
A8: Sesiones hechas | B8: =COUNTIF(Prospectos!$H$4:$H$203,"sesión hecha")
A9: Propuestas enviadas | B9: =COUNTIF(Prospectos!$H$4:$H$203,"propuesta enviada")
A10: Cerrados | B10: =COUNTIF(Prospectos!$H$4:$H$203,"cerrado") | C10: 2 | D10: objetivo del mes
A12: Hoy
A13: Toques que vencen hoy o antes | B13: =COUNTIFS(Prospectos!$G$4:$G$203,"<="&TODAY(),Prospectos!$H$4:$H$203,"<>cerrado")
A14: Abiertos sin próximo toque cargado | B14: =COUNTIFS(Prospectos!$A$4:$A$203,"<>",Prospectos!$G$4:$G$203,"",Prospectos!$H$4:$H$203,"abierto")
A16: Por origen | C16: la red tibia primero
A17: Tibios | B17: =COUNTIF(Prospectos!$C$4:$C$203,"T")
A18: Referidos | B18: =COUNTIF(Prospectos!$C$4:$C$203,"R")
A19: Fríos | B19: =COUNTIF(Prospectos!$C$4:$C$203,"F")
A20: Landing | B20: =COUNTIF(Prospectos!$C$4:$C$203,"L")
A22: Fuga total identificada
A23: Suma de "Total mensual" de los abiertos | B23: =SUMIFS(Prospectos!$O$4:$O$203,Prospectos!$H$4:$H$203,"abierto")
A26: La fila 3 de Prospectos es el ejemplo y no entra en ningún contador: los datos reales arrancan en la fila 4. Podés borrarla o dejarla.
